README.md
setup.py
tttimer/__init__.py
tttimer/cli_handler.py
tttimer/main.py
tttimer.egg-info/PKG-INFO
tttimer.egg-info/SOURCES.txt
tttimer.egg-info/dependency_links.txt
tttimer.egg-info/entry_points.txt
tttimer.egg-info/requires.txt
tttimer.egg-info/top_level.txt
tttimer/models/__init__.py
tttimer/models/report.py
tttimer/models/time_frame.py